LICENSE.txt
MANIFEST.in
README.md
pybmtools.c
pybmtools.h
setup.cfg
setup.py
libbm/.DS_Store
libbm/binaMeth.h
libbm/binaMethIO.h
libbm/bmCommon.h
libbm/bmRead.c
libbm/bmStats.c
libbm/bmValues.c
libbm/bmValues.h
libbm/bmWrite.c
libbm/io.c
libbm/regression.cpp
libbm/regression.hpp
pybmtest/__init__.py
pybmtest/test.bm
pybmtest/test.py
pybmtest/testnp.bm